tox_with_conda.py
tox_with_conda-1.0.6.dist-info/DESCRIPTION.rst
tox_with_conda-1.0.6.dist-info/LICENSE.txt
tox_with_conda-1.0.6.dist-info/METADATA
tox_with_conda-1.0.6.dist-info/RECORD
tox_with_conda-1.0.6.dist-info/WHEEL
tox_with_conda-1.0.6.dist-info/metadata.json
tox_with_conda-1.0.6.dist-info/top_level.txt
