Metadata-Version: 2.0
Name: tox-with-conda
Version: 1.0.6
Summary: Utility for making conda environments work with tox
Home-page: https://github.com/fauskanger/tox_with_conda
Author: Thomas Fauskanger
Author-email: UNKNOWN
License: MIT
Platform: UNKNOWN
